MANIFEST.in
README.md
requirements.txt
setup.py
prvsn.egg-info/PKG-INFO
prvsn.egg-info/SOURCES.txt
prvsn.egg-info/dependency_links.txt
prvsn.egg-info/top_level.txt
prvsnlib/__init__.py
prvsnlib/context.py
prvsnlib/log.py
prvsnlib/packager.py
prvsnlib/provisioner.py
prvsnlib/remote.py
prvsnlib/role.py
prvsnlib/runbook.py
prvsnlib/tasks/__init__.py
prvsnlib/tasks/command.py
prvsnlib/tasks/file.py
prvsnlib/tasks/filetype.py
prvsnlib/tasks/hostname.py
prvsnlib/tasks/kernel.py
prvsnlib/tasks/package.py
prvsnlib/tasks/zip.py
prvsnlib/utils/__init__.py
prvsnlib/utils/colors.py
prvsnlib/utils/file.py
prvsnlib/utils/run.py
prvsnlib/utils/ssh.py
prvsnlib/utils/string.py
prvsnlib/utils/timer.py
prvsnlib/utils/validation.py
prvsnlib/utils/zip.py
scripts/prvsn