Metadata-Version: 1.0
Name: prvsn
Version: 0.3
Summary: A simple provisioning tool
Home-page: https://github.com/acoomans/prvsn
Author: Arnaud Coomans
Author-email: hello@acoomans.com
License: BSD
Keywords: provision
Platform: any
